healthcare_agents/__init__.py
healthcare_agents/client.py
healthcare_agents/exceptions.py
healthcare_agents/models.py
oneliac-0.1.0.dist-info/METADATA
oneliac-0.1.0.dist-info/WHEEL
oneliac-0.1.0.dist-info/top_level.txt
oneliac-0.1.0.dist-info/RECORD
