Metadata-Version: 2.4
Name: oneliac
Version: 0.1.0
Summary: Python SDK for Privacy-Preserving Healthcare Agents API
Home-page: https://github.com/razaahmad9222/oneliac-python
Author: Raza Ahmad
Author-email: raza@healthcare-agents.com
Project-URL: Bug Reports, https://github.com/razaahmad9222/oneliac-python/issues
Project-URL: Source, https://github.com/razaahmad9222/oneliac-python
Project-URL: Documentation, https://healthcare-agents-sdk.readthedocs.io/
Project-URL: API Documentation, https://healthcare-agents-api.onrender.com/docs
Keywords: healthcare,privacy,zero-knowledge,blockchain,federated-learning,medical,api,sdk,hipaa,gdpr,solana
Classifier: Development Status :: 4 - Beta
Classifier: Intended Audience :: Developers
Classifier: Intended Audience :: Healthcare Industry
Classifier: License :: OSI Approved :: Apache Software License
Classifier: Operating System :: OS Independent
Classifier: Programming Language :: Python :: 3
Classifier: Programming Language :: Python :: 3.8
Classifier: Programming Language :: Python :: 3.9
Classifier: Programming Language :: Python :: 3.10
Classifier: Programming Language :: Python :: 3.11
Classifier: Programming Language :: Python :: 3.12
Classifier: Topic :: Software Development :: Libraries :: Python Modules
Classifier: Topic :: Scientific/Engineering :: Medical Science Apps.
Classifier: Topic :: Security :: Cryptography
Requires-Python: >=3.8
Requires-Dist: aiohttp>=3.9.0
Provides-Extra: dev
Requires-Dist: pytest>=7.0.0; extra == "dev"
Requires-Dist: pytest-asyncio>=0.21.0; extra == "dev"
Requires-Dist: black>=22.0.0; extra == "dev"
Requires-Dist: flake8>=4.0.0; extra == "dev"
Requires-Dist: mypy>=0.950; extra == "dev"
Provides-Extra: docs
Requires-Dist: sphinx>=4.0.0; extra == "docs"
Requires-Dist: sphinx-rtd-theme>=1.0.0; extra == "docs"
Dynamic: author
Dynamic: author-email
Dynamic: classifier
Dynamic: description
Dynamic: description-content-type
Dynamic: home-page
Dynamic: keywords
Dynamic: project-url
Dynamic: provides-extra
Dynamic: requires-dist
Dynamic: requires-python
Dynamic: summary
